<?xml version="1.0" encoding="UTF-8"?>
<metadata xml:lang="zh"><Esri><CreaDate>20241104</CreaDate><CreaTime>18045900</CreaTime><ArcGISFormat>1.0</ArcGISFormat><SyncOnce>TRUE</SyncOnce><DataProperties><lineage><Process ToolSource="e:\arcgispro\Resources\ArcToolbox\toolboxes\Conversion Tools.tbx\ExportFeatures" Date="20241104" Time="180459">ExportFeatures en.public.washington_polygon_building D:\csu-mapping\sample_data\part_of_washington_polygon_building.shp # NOT_USE_ALIAS "fid "fid" true true false 8 Double 8 38,First,#,en.public.washington_polygon_building,fid,-1,-1" #</Process></lineage></DataProperties></Esri></metadata>
